vector_2d/__init__.py
vector_2d/vector.py
vector_2d/vectorPolar.py
vector_2d-1.5.2.dist-info/LICENSE.txt
vector_2d-1.5.2.dist-info/METADATA
vector_2d-1.5.2.dist-info/WHEEL
vector_2d-1.5.2.dist-info/top_level.txt
vector_2d-1.5.2.dist-info/RECORD
