Metadata-Version: 2.1
Name: vector-2d
Version: 1.5.2
Summary: A module witch implements a two-dimensional vector, both in cartesian and polar coordinates.
Home-page: https://github.com/betados/vector_2d
Author: Alvaro Torres Ochaita
Author-email: torrestal@gmail.com
License: MIT
Keywords: vector,2d,physics,games,pygame,vector2d
Platform: UNKNOWN
